setup.cfg
setup.py
Flask_QSSession.egg-info/PKG-INFO
Flask_QSSession.egg-info/SOURCES.txt
Flask_QSSession.egg-info/dependency_links.txt
Flask_QSSession.egg-info/not-zip-safe
Flask_QSSession.egg-info/requires.txt
Flask_QSSession.egg-info/top_level.txt
flask_session/__init__.py
flask_session/sessions.py