Metadata-Version: 1.1
Name: Flask-QSSession
Version: 0.3.0
Summary: Add server-side session support for Flask application
Home-page: https://github.com/SiQLuxe/flask_session
Author: Lucas
Author-email: csq@qstrategy.cn
License: BSD
Download-URL: https://github.com/SiQLuxe/flask_session/tree/0.3.0
Platform: any
Classifier: Environment :: Web Environment
Classifier: Intended Audience :: Developers
Classifier: License :: OSI Approved :: BSD License
Classifier: Operating System :: OS Independent
Classifier: Programming Language :: Python :: 2
Classifier: Topic :: Internet :: WWW/HTTP :: Dynamic Content
Classifier: Topic :: Software Development :: Libraries :: Python Modules
